fiaas_logging/__init__.py
fiaas_logging-0.1.1.dist-info/LICENSE
fiaas_logging-0.1.1.dist-info/METADATA
fiaas_logging-0.1.1.dist-info/WHEEL
fiaas_logging-0.1.1.dist-info/top_level.txt
fiaas_logging-0.1.1.dist-info/zip-safe
fiaas_logging-0.1.1.dist-info/RECORD
