Metadata-Version: 2.1
Name: fiaas-logging
Version: 0.1.1
Summary: Python library for configuring logs in the FIAAS way
Home-page: https://github.com/fiaas/logging
Author: FIAAS developers
Author-email: fiaas@googlegroups.com
License: Apache License
Keywords: kubernetes fiaas logging
Platform: UNKNOWN
Classifier: Development Status :: 3 - Alpha
Classifier: Intended Audience :: Developers
Classifier: License :: OSI Approved :: Apache Software License
Classifier: Operating System :: OS Independent
Classifier: Programming Language :: Python
Classifier: Programming Language :: Python :: 2
Classifier: Programming Language :: Python :: 2.7
Classifier: Programming Language :: Python :: 3
Classifier: Programming Language :: Python :: 3.6
Classifier: Programming Language :: Python :: 3.7
Classifier: Programming Language :: Python :: 3.8
Classifier: Topic :: Internet
Classifier: Topic :: Software Development :: Libraries :: Python Modules
Provides-Extra: dev
Requires-Dist: pytest (==4.6.9) ; extra == 'dev'
Requires-Dist: pytest-cov (==2.8.1) ; extra == 'dev'
Requires-Dist: pytest-html (==1.22.1) ; extra == 'dev'
Requires-Dist: pytest-sugar (==0.9.2) ; extra == 'dev'
Requires-Dist: callee (==0.3.1) ; extra == 'dev'
Requires-Dist: mock (==3.0.5) ; extra == 'dev'
Requires-Dist: prospector ; extra == 'dev'
Provides-Extra: release
Requires-Dist: publish ; extra == 'release'
